<?xml version="1.0"?>
<assessmentItems>
	<assessmentItem subject="Web" author="jvadillo001@ikasle.ehu.eus">
		<itemBody>
			<p>Tag HTML para a&#xF1;adir un formulario</p>
		</itemBody>
		<correctResponse>
			<value>
				FORM
			</value>
		</correctResponse>
		<incorrectResponses>
			<value> OBJECT </value>
			<value> TABLE </value>
			<value> DIV </value>
		</incorrectResponses>
	</assessmentItem>
	<assessmentItem subject="Internet" author="rarruabarrena001@ikasle.ehu.eus">
		<itemBody>
			<p>Este protocolo acabar&#xE1; funcionando
			incluso entre dos latas unidas por un cord&#xF3;n</p>
		</itemBody>
		<correctResponse>
			<value>
				TCP/IP
			</value>
		</correctResponse>
		<incorrectResponses>
			<value> HTTP </value>
			<value> SMTP </value>
			<value> Ninguna es correcta </value>
		</incorrectResponses>
	</assessmentItem>
<assessmentItem subject="saludo" author="tomas001@ikasle.ehu.eus"><itemBody><p>holaholahola</p></itemBody><correctResponse><value>chauchauchau</value></correctResponse><incorrectResponses><value>asdasd</value><value>asdasd</value><value>asdasd</value></incorrectResponses></assessmentItem><assessmentItem subject="futbol" author="tomas001@ikasle.ehu.eus"><itemBody><p>equipo mas grande</p></itemBody><correctResponse><value>river</value></correctResponse><incorrectResponses><value>boca</value><value>penarol</value><value>nacional</value></incorrectResponses></assessmentItem><assessmentItem subject="comida" author="tomas001@ikasle.ehu.eus"><itemBody><p>verduras o frutas</p></itemBody><correctResponse><value>lechuga</value></correctResponse><incorrectResponses><value>pollo</value><value>cerdo</value><value>pescado</value></incorrectResponses></assessmentItem><assessmentItem subject="hola" author="tom000@ikasle.ehu.eus"><itemBody><p>hola com oestas</p></itemBody><correctResponse><value>saludo</value></correctResponse><incorrectResponses><value>1</value><value>1</value><value>1</value></incorrectResponses></assessmentItem><assessmentItem subject="tema" author="fed123@ikasle.ehu.eus"><itemBody><p>enunciadodepregunts</p></itemBody><correctResponse><value>correcto</value></correctResponse><incorrectResponses><value>inc</value><value>inc</value><value>inc</value></incorrectResponses></assessmentItem><assessmentItem subject="tema" author="fed123@ikasle.ehu.eus"><itemBody><p>elementodepreguntanuevo</p></itemBody><correctResponse><value>cor</value></correctResponse><incorrectResponses><value>inc</value><value>inc</value><value>inc</value></incorrectResponses></assessmentItem><assessmentItem subject="tema" author="fed123@ikasle.ehu.eus"><itemBody><p>nuevaaaaaaaaaaaaaaaaaa</p></itemBody><correctResponse><value>cor</value></correctResponse><incorrectResponses><value>cor</value><value>cor</value><value>cor</value></incorrectResponses></assessmentItem><assessmentItem subject="eee" author="fed123@ikasle.ehu.eus"><itemBody><p>aaaaaaaaaaaaaaaaaaaaaa</p></itemBody><correctResponse><value>aaaaaa</value></correctResponse><incorrectResponses><value>a</value><value>a</value><value>a</value></incorrectResponses></assessmentItem><assessmentItem subject="1" author="fed123@ikasle.ehu.eus"><itemBody><p>aaaaaaaaaaaaaaaaaaaaaaaaa</p></itemBody><correctResponse><value>a</value></correctResponse><incorrectResponses><value>a</value><value>aa</value><value>a</value></incorrectResponses></assessmentItem><assessmentItem subject="a" author="fed123@ikasle.ehu.eus"><itemBody><p>sasas</p></itemBody><correctResponse><value>as</value></correctResponse><incorrectResponses><value>sa</value><value>aaaaaaaaaaaaaaaaaaaaaaaa</value><value>a</value></incorrectResponses></assessmentItem><assessmentItem subject="a" author="fed123@ikasle.ehu.eus"><itemBody><p>sasasaaaaaaaaaaaaaaa</p></itemBody><correctResponse><value>as</value></correctResponse><incorrectResponses><value>sa</value><value>aaaaaaaaaaaaaaaaaaaaaaaa</value><value>a</value></incorrectResponses></assessmentItem><assessmentItem subject="tena" author="fed123@ikasle.ehu.eus"><itemBody><p>enunciadodelapregunta</p></itemBody><correctResponse><value>cor</value></correctResponse><incorrectResponses><value>inc</value><value>inc</value><value>inc</value></incorrectResponses></assessmentItem><assessmentItem subject="1" author="fed123@ikasle.ehu.eus"><itemBody><p>enunciadonueov</p></itemBody><correctResponse><value>correcto</value></correctResponse><incorrectResponses><value>iinc</value><value>inc</value><value>inci</value></incorrectResponses></assessmentItem><assessmentItem subject="tema" author="fed123@ikasle.ehu.eus"><itemBody><p>1234</p></itemBody><correctResponse><value>dw</value></correctResponse><incorrectResponses><value>wd</value><value>wd</value><value>wd</value></incorrectResponses></assessmentItem><assessmentItem subject="tema" author="fed123@ikasle.ehu.eus"><itemBody><p>1234658789010</p></itemBody><correctResponse><value>dw</value></correctResponse><incorrectResponses><value>wd</value><value>wd</value><value>wd</value></incorrectResponses></assessmentItem><assessmentItem subject="a" author="fed123@ikasle.ehu.eus"><itemBody><p>1234567891011</p></itemBody><correctResponse><value>corr</value></correctResponse><incorrectResponses><value>inc</value><value>inc</value><value>inc</value></incorrectResponses></assessmentItem><assessmentItem subject="tena" author="fed123@ikasle.ehu.eus"><itemBody><p>enunciadoconmas</p></itemBody><correctResponse><value>cor</value></correctResponse><incorrectResponses><value>inc</value><value>inc</value><value>inc</value></incorrectResponses></assessmentItem><assessmentItem subject="1" author="fed123@ikasle.ehu.eus"><itemBody><p>elemenctocomasde10</p></itemBody><correctResponse><value>tabla</value></correctResponse><incorrectResponses><value>1</value><value>1</value><value>1</value></incorrectResponses></assessmentItem><assessmentItem subject="1" author="fed123@ikasle.ehu.eus"><itemBody><p>nuevo1111111111111111111</p></itemBody><correctResponse><value>1</value></correctResponse><incorrectResponses><value>1</value><value>1</value><value>1</value></incorrectResponses></assessmentItem><assessmentItem subject="t" author="fedee123@ikasle.ehu.eus"><itemBody><p>enunciadodelapregunta</p></itemBody><correctResponse><value>cor</value></correctResponse><incorrectResponses><value>inc</value><value>inc</value><value>inc</value></incorrectResponses></assessmentItem><assessmentItem subject="1" author="fedee123@ikasle.ehu.eus"><itemBody><p>111111111111111111111111111</p></itemBody><correctResponse><value>1</value></correctResponse><incorrectResponses><value>1</value><value>1</value><value>1</value></incorrectResponses></assessmentItem><assessmentItem subject="1" author="fedee123@ikasle.ehu.eus"><itemBody><p>saaaaaaaaaaaaaaaaaa</p></itemBody><correctResponse><value>cor</value></correctResponse><incorrectResponses><value>1</value><value>1</value><value>1</value></incorrectResponses></assessmentItem><assessmentItem subject="1" author="fedee123@ikasle.ehu.eus"><itemBody><p>aaaaaaaaaaaaaaaaaaaa</p></itemBody><correctResponse><value>1</value></correctResponse><incorrectResponses><value>1</value><value>1</value><value>a</value></incorrectResponses></assessmentItem><assessmentItem subject="tema" author="fede000@ikasle.ehu.eus"><itemBody><p>enunciadodelapregunta</p></itemBody><correctResponse><value>cor</value></correctResponse><incorrectResponses><value>inc</value><value>inc</value><value>inc</value></incorrectResponses></assessmentItem><assessmentItem subject="gestion" author="fede000@ikasle.ehu.eus"><itemBody><p>enunciadodelapreguntaaaaaaaaaaaaaa</p></itemBody><correctResponse><value>1</value></correctResponse><incorrectResponses><value>1</value><value>1</value><value>1</value></incorrectResponses></assessmentItem><assessmentItem subject="te" author="fede000@ikasle.ehu.eus"><itemBody><p>holaaaaaaaaaaaaaaaaaaaa</p></itemBody><correctResponse><value>cor</value></correctResponse><incorrectResponses><value>cor</value><value>corc</value><value>cor</value></incorrectResponses></assessmentItem><assessmentItem subject="2" author="fede000@ikasle.ehu.eus"><itemBody><p>enunciadoporgestion</p></itemBody><correctResponse><value>cor</value></correctResponse><incorrectResponses><value>inc</value><value>inc</value><value>inc</value></incorrectResponses></assessmentItem><assessmentItem subject="NO" author="fede000@ikasle.ehu.eus"><itemBody><p>asddefaaaaaaaaaaaaa</p></itemBody><correctResponse><value>ahorasi</value></correctResponse><incorrectResponses><value>dale</value><value>NO</value><value>NO</value></incorrectResponses></assessmentItem><assessmentItem subject="1" author="fed123@ikasle.ehu.eus"><itemBody><p>sadsdssssssssssssssssssssssssssssssssssssss</p></itemBody><correctResponse><value>corrctaaaaaaa</value></correctResponse><incorrectResponses><value>1</value><value>1</value><value>1</value></incorrectResponses></assessmentItem><assessmentItem subject="1" author="fed123@ikasle.ehu.eus"><itemBody><p>enunicadoporinsertarrrrr</p></itemBody><correctResponse><value>cor</value></correctResponse><incorrectResponses><value>inc</value><value>inc</value><value>inc</value></incorrectResponses></assessmentItem><assessmentItem subject="1" author="nuev000@ikasle.ehu.eus"><itemBody><p>111111111111111111111111111111</p></itemBody><correctResponse><value>1</value></correctResponse><incorrectResponses><value>1</value><value>1</value><value>1</value></incorrectResponses></assessmentItem><assessmentItem subject="2" author="nuev000@ikasle.ehu.eus"><itemBody><p>2222222222222222222222222222</p></itemBody><correctResponse><value>2</value></correctResponse><incorrectResponses><value>2</value><value>2</value><value>2</value></incorrectResponses></assessmentItem><assessmentItem subject="3" author="nuev000@ikasle.ehu.eus"><itemBody><p>333333333333333333333333</p></itemBody><correctResponse><value>3</value></correctResponse><incorrectResponses><value>3</value><value>3</value><value>3</value></incorrectResponses></assessmentItem></assessmentItems>
